twisted/plugins/txasgi.py
txasgiresource/__init__.py
txasgiresource/application.py
txasgiresource/asgiresource.py
txasgiresource/http.py
txasgiresource/manager.py
txasgiresource/scheduler.py
txasgiresource/utils.py
txasgiresource/ws.py
txasgiresource/tests/__init__.py
txasgiresource/tests/test_asgiresource.py
txasgiresource/tests/test_http.py
txasgiresource/tests/test_scheduler.py
txasgiresource/tests/test_ws.py
txasgiresource/tests/utils.py
txasgiresource-2.2.1.dist-info/LICENSE
txasgiresource-2.2.1.dist-info/METADATA
txasgiresource-2.2.1.dist-info/WHEEL
txasgiresource-2.2.1.dist-info/top_level.txt
txasgiresource-2.2.1.dist-info/RECORD
