Metadata-Version: 2.1
Name: txasgiresource
Version: 2.2.1
Summary: ASGI implemented as a Twisted resource
Home-page: https://github.com/JohnDoee/txasgiresource
Author: Anders Jensen
Author-email: johndoee@tidalstream.org
License: MIT
Platform: UNKNOWN
Classifier: Development Status :: 4 - Beta
Classifier: Environment :: Web Environment
Classifier: Framework :: Twisted
Classifier: Intended Audience :: Developers
Classifier: License :: OSI Approved :: MIT License
Classifier: Operating System :: OS Independent
Classifier: Programming Language :: Python
Classifier: Programming Language :: Python :: 3
Classifier: Programming Language :: Python :: 3.6
Classifier: Programming Language :: Python :: 3.7
Classifier: Programming Language :: Python :: 3.8
Classifier: Topic :: Internet :: WWW/HTTP
Classifier: Topic :: Software Development :: Libraries :: Python Modules
Requires-Dist: twisted (>=16.0)
Requires-Dist: autobahn (>=0.12)
Requires-Dist: asgiref (>=2.3.2)
